dev_swiper/__init__.py
dev_swiper/main.py
dev_swiper-0.0.5.dist-info/LICENSE
dev_swiper-0.0.5.dist-info/METADATA
dev_swiper-0.0.5.dist-info/WHEEL
dev_swiper-0.0.5.dist-info/entry_points.txt
dev_swiper-0.0.5.dist-info/top_level.txt
dev_swiper-0.0.5.dist-info/RECORD
