Metadata-Version: 2.1
Name: dev-swiper
Version: 0.0.5
Summary: Stronger swiping game for devs
Home-page: https://github.com/DipanshKhandelwal/dev-swiper
Author: Dipansh Khandelwal
Author-email: dipanshkhandelwal@gmail.com
License: UNKNOWN
Platform: UNKNOWN
Classifier: Programming Language :: Python :: 3
Classifier: License :: OSI Approved :: MIT License
Classifier: Operating System :: OS Independent
Requires-Dist: docopt
